sensetable/__init__.py
sensetable/app.py
sensetable/local_file_system.py
sensetable/pages.py
sensetable/query.py
sensetable/s3.py
sensetable/settings.py
sensetable/statics/.DS_Store
sensetable/statics/404.html
sensetable/statics/FolderBrowser.html
sensetable/statics/FolderBrowser.txt
sensetable/statics/S-dark.svg
sensetable/statics/S-light.svg
sensetable/statics/SenseTable-dark.svg
sensetable/statics/SenseTable-light.svg
sensetable/statics/Table.html
sensetable/statics/Table.txt
sensetable/statics/index.html
sensetable/statics/index.txt
sensetable/statics/_next/static/9qQ75Yyc4MUEgvor1HtL2/_buildManifest.js
sensetable/statics/_next/static/9qQ75Yyc4MUEgvor1HtL2/_ssgManifest.js
sensetable/statics/_next/static/chunks/115-5f1137a3079d919f.js
sensetable/statics/_next/static/chunks/117-3d47e67a9f1f49ae.js
sensetable/statics/_next/static/chunks/190-d4f831a303fe21e1.js
sensetable/statics/_next/static/chunks/458d1a22-48047afa702c6bc4.js
sensetable/statics/_next/static/chunks/476.1a20f81a3a9aea91.js
sensetable/statics/_next/static/chunks/49c48124-1c1e6c2e129a1eac.js
sensetable/statics/_next/static/chunks/534.f00a7d79b115cfc7.js
sensetable/statics/_next/static/chunks/589.d72cf90697e1336a.js
sensetable/statics/_next/static/chunks/600-e10d757a393c7b6b.js
sensetable/statics/_next/static/chunks/682.d25189b5d14e23e5.js
sensetable/statics/_next/static/chunks/813.1530daf9a49708c3.js
sensetable/statics/_next/static/chunks/880.2a9be373774be332.js
sensetable/statics/_next/static/chunks/975-acbbba8d88bb70a5.js
sensetable/statics/_next/static/chunks/980-5de94a90042a759b.js
sensetable/statics/_next/static/chunks/ad84e7c0-f02b8ca5110187d3.js
sensetable/statics/_next/static/chunks/b11f63c4-4b2e1169b08ad87c.js
sensetable/statics/_next/static/chunks/b7059e3b-0fa57fbd6dc89beb.js
sensetable/statics/_next/static/chunks/d9e1935d.2bd1b1b97ce30238.js
sensetable/statics/_next/static/chunks/e31c3f77-046d008c5ce7a978.js
sensetable/statics/_next/static/chunks/framework-23289c1a7a5e85da.js
sensetable-0.0.1rc1.dist-info/METADATA
sensetable-0.0.1rc1.dist-info/WHEEL
sensetable-0.0.1rc1.dist-info/top_level.txt
sensetable-0.0.1rc1.dist-info/RECORD
