Metadata-Version: 2.4
Name: sensetable
Version: 0.0.1rc1
Summary: Smoothly make sense of your large-scale multi-modal tabular data
Requires-Python: >=3.9
Requires-Dist: boto3>=1.39.11
Requires-Dist: duckdb>=1.2.1
Requires-Dist: flask>=3.1.0
Requires-Dist: flask-cors>=5.0.1
Requires-Dist: gunicorn>=23.0.0
Requires-Dist: pydantic>=2.11.7
Requires-Dist: pytz>=2025.2
Requires-Dist: requests>=2.32.3
Requires-Dist: rich>=14.0.0
